etsy_py/__init__.py
etsy_py/api.py
etsy_py/exceptions.py
etsy_py-1.0.0.dist-info/DESCRIPTION.rst
etsy_py-1.0.0.dist-info/METADATA
etsy_py-1.0.0.dist-info/RECORD
etsy_py-1.0.0.dist-info/WHEEL
etsy_py-1.0.0.dist-info/metadata.json
etsy_py-1.0.0.dist-info/top_level.txt
