Metadata-Version: 1.1
Name: etsy-py
Version: 1.0.0
Summary: Python2 & Python3 module for Etsy's API.
Home-page: https://github.com/jaddison/etsy_py
Author: James Addison
Author-email: addi00+github.com@gmail.com
License: BSD
Platform: UNKNOWN
Classifier: Development Status :: 4 - Beta
Classifier: Intended Audience :: Developers
Classifier: Programming Language :: Python :: 2
Classifier: Programming Language :: Python :: 2.7
Classifier: Programming Language :: Python :: 3
Classifier: Programming Language :: Python :: 3.3
Classifier: Programming Language :: Python :: 3.4
Classifier: Programming Language :: Python :: 3.5
Classifier: Programming Language :: Python :: 3.6
